exePackage/XMLtoCSVConvert.py
exeopen-1.1.0.dist-info/LICENSE.txt
exeopen-1.1.0.dist-info/METADATA
exeopen-1.1.0.dist-info/WHEEL
exeopen-1.1.0.dist-info/top_level.txt
exeopen-1.1.0.dist-info/RECORD
